weighted_sample_statistics/__init__.py
weighted_sample_statistics/core.py
weighted_sample_statistics/main.py
weighted_sample_statistics-0.2.3.dist-info/LICENSE.txt
weighted_sample_statistics-0.2.3.dist-info/METADATA
weighted_sample_statistics-0.2.3.dist-info/WHEEL
weighted_sample_statistics-0.2.3.dist-info/top_level.txt
weighted_sample_statistics-0.2.3.dist-info/RECORD
