Metadata-Version: 2.1
Name: weighted_sample_statistics
Version: 0.2.3
Summary: Calculate statistics in dataframes using weighting functions
Home-page: https://github.com/eelcovv/WeightedSampleStatistics
Author: Eelco van Vliet
Author-email: eelcovv@gmail.com
License: MIT
Project-URL: Documentation, https://weightedsamplestatistics.readthedocs.io/en/latest/
Platform: any
Classifier: Development Status :: 4 - Beta
Classifier: Programming Language :: Python
License-File: LICENSE.txt
Requires-Dist: importlib-metadata; python_version < "3.8"
Requires-Dist: numpy
Requires-Dist: pandas
Provides-Extra: dev
Requires-Dist: tox; extra == "dev"
Requires-Dist: pyscaffold; extra == "dev"
Requires-Dist: pre-commit; extra == "dev"
Requires-Dist: black; extra == "dev"
Requires-Dist: setuptools; extra == "dev"
Requires-Dist: pytest; extra == "dev"
Requires-Dist: pytest-cov; extra == "dev"
Provides-Extra: testing
Requires-Dist: setuptools; extra == "testing"
Requires-Dist: pytest; extra == "testing"
Requires-Dist: pytest-cov; extra == "testing"
